nobitexv2/__init__.py
nobitexv2/nobitexv2.py
nobitexv2-0.2.0.dist-info/licenses/LICENSE
nobitexv2-0.2.0.dist-info/METADATA
nobitexv2-0.2.0.dist-info/WHEEL
nobitexv2-0.2.0.dist-info/top_level.txt
nobitexv2-0.2.0.dist-info/RECORD
