Metadata-Version: 2.4
Name: nobitexv2
Version: 0.2.0
Summary: Nobitex client for python
Home-page: https://github.com/navidpgg/nobitexv2
Author: NavidP
Author-email: navidpoladi99@example.com
Classifier: Programming Language :: Python :: 3
Classifier: License :: OSI Approved :: MIT License
Classifier: Operating System :: OS Independent
Requires-Python: >=3.6
License-File: LICENSE
Requires-Dist: requests>=2
Dynamic: author
Dynamic: author-email
Dynamic: classifier
Dynamic: description
Dynamic: description-content-type
Dynamic: home-page
Dynamic: license-file
Dynamic: requires-dist
Dynamic: requires-python
Dynamic: summary
